opencmp/__init__.py
opencmp/__main__.py
opencmp/entry_points.py
opencmp/run.py
opencmp/config_functions/__init__.py
opencmp/config_functions/base_config_functions.py
opencmp/config_functions/boundary_conditions.py
opencmp/config_functions/controller_functions.py
opencmp/config_functions/expanded_config_parser.py
opencmp/config_functions/initial_conditions.py
opencmp/config_functions/load_config.py
opencmp/config_functions/model_functions.py
opencmp/config_functions/parse_arithmetic.py
opencmp/config_functions/reference_solutions.py
opencmp/controllers/__init__.py
opencmp/controllers/base_controller.py
opencmp/controllers/controller_group.py
opencmp/controllers/misc.py
opencmp/controllers/pid_controller.py
opencmp/diffuse_interface/__init__.py
opencmp/diffuse_interface/dim.py
opencmp/diffuse_interface/interface.py
opencmp/diffuse_interface/mesh_helpers.py
opencmp/diffuse_interface/mesh_quality_metrics.py
opencmp/helpers/__init__.py
opencmp/helpers/dg.py
opencmp/helpers/error.py
opencmp/helpers/io.py
opencmp/helpers/math.py
opencmp/helpers/mesh.py
opencmp/helpers/misc.py
opencmp/helpers/ngsolve_.py
opencmp/helpers/saving.py
opencmp/helpers/testing.py
opencmp/models/__init__.py
opencmp/models/base_model.py
opencmp/models/ins.py
opencmp/models/ins_dim.py
opencmp/models/misc.py
opencmp/models/multi_component_ins.py
opencmp/models/poisson.py
opencmp/models/poisson_dim.py
opencmp/models/stokes.py
opencmp/models/stokes_dim.py
opencmp/post_processing/__init__.py
opencmp/post_processing/error_analysis.py
opencmp/post_processing/output_conversions.py
opencmp/solvers/__init__.py
opencmp/solvers/base_solver.py
opencmp/solvers/misc.py
opencmp/solvers/stationary.py
opencmp/solvers/time_integration_schemes.py
opencmp/solvers/transient_RK.py
opencmp/solvers/transient_multistep.py
opencmp/solvers/adaptive_transient_solvers/__init__.py
opencmp/solvers/adaptive_transient_solvers/adaptive_IMEX.py
opencmp/solvers/adaptive_transient_solvers/adaptive_three_step.py
opencmp-1.0.2.dist-info/AUTHORS.md
opencmp-1.0.2.dist-info/LICENSE.md
opencmp-1.0.2.dist-info/METADATA
opencmp-1.0.2.dist-info/WHEEL
opencmp-1.0.2.dist-info/entry_points.txt
opencmp-1.0.2.dist-info/top_level.txt
opencmp-1.0.2.dist-info/RECORD
