Metadata-Version: 2.1
Name: opencmp
Version: 1.0.2
Summary: OpenCMP is a computational multiphysics software package based on the finite element method.
License: BSD 3-Clause License
Keywords: multiphysics,simulation
Classifier: Topic :: Scientific/Engineering :: Physics
Classifier: License :: OSI Approved :: GNU Lesser General Public License v2 or later (LGPLv2+)
Classifier: Programming Language :: Python :: 3 :: Only
License-File: LICENSE.md
License-File: AUTHORS.md
Requires-Dist: numpy ; python_version > "3.7.0"
Requires-Dist: scipy ; python_version > "3.7.0"
Requires-Dist: ngsolve ; python_version > "3.7.0"
Requires-Dist: configparser ; python_version > "3.7.0"
Requires-Dist: pyparsing ; python_version > "3.7.0"
Provides-Extra: all
Requires-Dist: pytest ; (python_version > "3.7") and extra == 'all'
Requires-Dist: pytest-xdist ; (python_version > "3.7") and extra == 'all'
Requires-Dist: tabulate ; (python_version > "3.7") and extra == 'all'
Requires-Dist: edt ; (python_version > "3.7") and extra == 'all'
Provides-Extra: edt
Requires-Dist: edt ; (python_version > "3.7") and extra == 'edt'
Provides-Extra: tab
Requires-Dist: tabulate ; (python_version > "3.7") and extra == 'tab'
Provides-Extra: test
Requires-Dist: pytest ; (python_version > "3.7") and extra == 'test'
Provides-Extra: test_ext
Requires-Dist: pytest ; (python_version > "3.7") and extra == 'test_ext'
Requires-Dist: pytest-xdist ; (python_version > "3.7") and extra == 'test_ext'
